<?xml version="1.0" encoding="UTF-8"?>
<con:soapui-project name="BidServiceClient" resourceRoot="" soapui-version="3.6.1" xmlns:con="http://eviware.com/soapui/config"><con:settings/><con:interface xsi:type="con:WsdlInterface" wsaVersion="NONE" name="ApiBidPortBinding" type="wsdl" bindingName="{http://www.auction.com/api/adf/bidservice/service}ApiBidPortBinding" soapVersion="1_1" anonymous="optional" definition="http://10.207.67.239:7011/BidService/ApiBidService?WSDL" xmlns:xsi="http://www.w3.org/2001/XMLSchema-instance"><con:settings/><con:definitionCache type="TEXT" rootPart="http://10.207.67.239:7011/BidService/ApiBidService?WSDL"><con:part><con:url>http://10.207.67.239:7011/BidService/ApiBidService?WSDL</con:url><con:content><![CDATA[<!--Published by JAX-WS RI at http://jax-ws.dev.java.net. RI's version is Oracle JAX-WS 2.1.5.-->
<!--Generated by JAX-WS RI at http://jax-ws.dev.java.net. RI's version is Oracle JAX-WS 2.1.5.-->
<definitions targetNamespace="http://www.auction.com/api/adf/bidservice/service" name="ApiBidService" xmlns:soap="http://schemas.xmlsoap.org/wsdl/soap/" xmlns:tns="http://www.auction.com/api/adf/bidservice/service" xmlns:xsd="http://www.w3.org/2001/XMLSchema" xmlns="http://schemas.xmlsoap.org/wsdl/">
  <types>
    <xsd:schema>
      <xsd:import namespace="http://www.auction.com/api/adf/runtimeFault" schemaLocation="http://10.207.67.239:7011/BidService/ApiBidService?xsd=1"/>
    </xsd:schema>
    <xsd:schema>
      <xsd:import namespace="http://www.auction.com/api/adf/bidservice/service" schemaLocation="http://10.207.67.239:7011/BidService/ApiBidService?xsd=2"/>
    </xsd:schema>
    <xsd:schema>
      <xsd:import namespace="http://www.auction.com/api/adf/bidservice/ebo" schemaLocation="http://10.207.67.239:7011/BidService/ApiBidService?xsd=3"/>
    </xsd:schema>
    <xsd:schema>
      <xsd:import namespace="http://www.auction.com/api/adf/bidservice/ebm" schemaLocation="http://10.207.67.239:7011/BidService/ApiBidService?xsd=4"/>
    </xsd:schema>
  </types>
  <message name="addNewBid">
    <part name="parameters" element="ns1:addNewBid" xmlns:ns1="http://www.auction.com/api/adf/bidservice/ebm"/>
  </message>
  <message name="addNewBidResponse">
    <part name="parameters" element="ns2:addNewBidResponse" xmlns:ns2="http://www.auction.com/api/adf/bidservice/ebm"/>
  </message>
  <message name="ActionServiceException">
    <part name="fault" element="ns3:runtimeFaultMessage" xmlns:ns3="http://www.auction.com/api/adf/runtimeFault"/>
  </message>
  <message name="changeBidAmount">
    <part name="parameters" element="tns:changeBidAmount"/>
  </message>
  <message name="changeBidAmountResponse">
    <part name="parameters" element="tns:changeBidAmountResponse"/>
  </message>
  <message name="removeBid">
    <part name="parameters" element="tns:removeBid"/>
  </message>
  <message name="removeBidResponse">
    <part name="parameters" element="tns:removeBidResponse"/>
  </message>
  <message name="getAllBids">
    <part name="parameters" element="tns:getAllBids"/>
  </message>
  <message name="getAllBidsResponse">
    <part name="parameters" element="tns:getAllBidsResponse"/>
  </message>
  <message name="getHigherBids">
    <part name="parameters" element="tns:getHigherBids"/>
  </message>
  <message name="getHigherBidsResponse">
    <part name="parameters" element="tns:getHigherBidsResponse"/>
  </message>
  <portType name="ApiBid">
    <operation name="addNewBid">
      <input message="tns:addNewBid"/>
      <output message="tns:addNewBidResponse"/>
      <fault message="tns:ActionServiceException" name="ActionServiceException"/>
    </operation>
    <operation name="changeBidAmount">
      <input message="tns:changeBidAmount"/>
      <output message="tns:changeBidAmountResponse"/>
      <fault message="tns:ActionServiceException" name="ActionServiceException"/>
    </operation>
    <operation name="removeBid">
      <input message="tns:removeBid"/>
      <output message="tns:removeBidResponse"/>
      <fault message="tns:ActionServiceException" name="ActionServiceException"/>
    </operation>
    <operation name="getAllBids">
      <input message="tns:getAllBids"/>
      <output message="tns:getAllBidsResponse"/>
      <fault message="tns:ActionServiceException" name="ActionServiceException"/>
    </operation>
    <operation name="getHigherBids">
      <input message="tns:getHigherBids"/>
      <output message="tns:getHigherBidsResponse"/>
      <fault message="tns:ActionServiceException" name="ActionServiceException"/>
    </operation>
  </portType>
  <binding name="ApiBidPortBinding" type="tns:ApiBid">
    <soap:binding transport="http://schemas.xmlsoap.org/soap/http" style="document"/>
    <operation name="addNewBid">
      <soap:operation soapAction="http://localhost.localdomain:7011/BidService/ApiBidService/addNewBid"/>
      <input>
        <soap:body use="literal"/>
      </input>
      <output>
        <soap:body use="literal"/>
      </output>
      <fault name="ActionServiceException">
        <soap:fault name="ActionServiceException" use="literal"/>
      </fault>
    </operation>
    <operation name="changeBidAmount">
      <soap:operation soapAction="http://localhost.localdomain:7011/BidService/ApiBidService/changeBid"/>
      <input>
        <soap:body use="literal"/>
      </input>
      <output>
        <soap:body use="literal"/>
      </output>
      <fault name="ActionServiceException">
        <soap:fault name="ActionServiceException" use="literal"/>
      </fault>
    </operation>
    <operation name="removeBid">
      <soap:operation soapAction="http://localhost.localdomain:7011/BidService/ApiBidService/removeBid"/>
      <input>
        <soap:body use="literal"/>
      </input>
      <output>
        <soap:body use="literal"/>
      </output>
      <fault name="ActionServiceException">
        <soap:fault name="ActionServiceException" use="literal"/>
      </fault>
    </operation>
    <operation name="getAllBids">
      <soap:operation soapAction="http://localhost.localdomain:7011/BidService/ApiBidService/allBids"/>
      <input>
        <soap:body use="literal"/>
      </input>
      <output>
        <soap:body use="literal"/>
      </output>
      <fault name="ActionServiceException">
        <soap:fault name="ActionServiceException" use="literal"/>
      </fault>
    </operation>
    <operation name="getHigherBids">
      <soap:operation soapAction="http://localhost.localdomain:7011/BidService/ApiBidService/higherBids"/>
      <input>
        <soap:body use="literal"/>
      </input>
      <output>
        <soap:body use="literal"/>
      </output>
      <fault name="ActionServiceException">
        <soap:fault name="ActionServiceException" use="literal"/>
      </fault>
    </operation>
  </binding>
  <service name="ApiBidService">
    <port name="ApiBidPort" binding="tns:ApiBidPortBinding">
      <soap:address location="http://10.207.67.239:7011/BidService/ApiBidService"/>
    </port>
  </service>
</definitions>]]></con:content><con:type>http://schemas.xmlsoap.org/wsdl/</con:type></con:part><con:part><con:url>http://10.207.67.239:7011/BidService/ApiBidService?xsd=1</con:url><con:content><![CDATA[<!--Published by JAX-WS RI at http://jax-ws.dev.java.net. RI's version is Oracle JAX-WS 2.1.5.-->
<xs:schema version="1.0" targetNamespace="http://www.auction.com/api/adf/runtimeFault" xmlns:xs="http://www.w3.org/2001/XMLSchema">
  <xs:element name="runtimeFaultMessage">
    <xs:complexType>
      <xs:sequence>
        <xs:element name="code" type="xs:string" form="qualified"/>
        <xs:element name="summary" type="xs:string" form="qualified"/>
        <xs:element name="detail" form="qualified">
          <xs:complexType>
            <xs:sequence>
              <xs:element name="message" type="xs:string" form="qualified"/>
              <xs:element name="originalPayload" type="xs:anyType" form="qualified"/>
              <xs:element name="coreFault" type="xs:anyType" form="qualified"/>
            </xs:sequence>
          </xs:complexType>
        </xs:element>
      </xs:sequence>
    </xs:complexType>
  </xs:element>
</xs:schema>]]></con:content><con:type>http://www.w3.org/2001/XMLSchema</con:type></con:part><con:part><con:url>http://10.207.67.239:7011/BidService/ApiBidService?xsd=2</con:url><con:content><![CDATA[<!--Published by JAX-WS RI at http://jax-ws.dev.java.net. RI's version is Oracle JAX-WS 2.1.5.-->
<xs:schema version="1.0" targetNamespace="http://www.auction.com/api/adf/bidservice/service" xmlns:tns="http://www.auction.com/api/adf/bidservice/service" xmlns:ns1="http://www.auction.com/api/adf/bidservice/ebm" xmlns:xs="http://www.w3.org/2001/XMLSchema">
  <xs:import namespace="http://www.auction.com/api/adf/bidservice/ebm" schemaLocation="http://10.207.67.239:7011/BidService/ApiBidService?xsd=4"/>
  <xs:element name="changeBidAmount" type="tns:changeBidAmount"/>
  <xs:element name="changeBidAmountResponse" type="tns:changeBidAmountResponse"/>
  <xs:element name="getAllBids" type="tns:getAllBids"/>
  <xs:element name="getAllBidsResponse" type="tns:getAllBidsResponse"/>
  <xs:element name="getHigherBids" type="tns:getHigherBids"/>
  <xs:element name="getHigherBidsResponse" type="tns:getHigherBidsResponse"/>
  <xs:element name="removeBid" type="tns:removeBid"/>
  <xs:element name="removeBidResponse" type="tns:removeBidResponse"/>
  <xs:complexType name="getHigherBids">
    <xs:sequence>
      <xs:element name="amountHigherThan" type="xs:double"/>
    </xs:sequence>
  </xs:complexType>
  <xs:complexType name="getHigherBidsResponse">
    <xs:sequence>
      <xs:element ref="ns1:getHighBidsResponse" minOccurs="0" maxOccurs="unbounded"/>
    </xs:sequence>
  </xs:complexType>
  <xs:complexType name="removeBid">
    <xs:sequence>
      <xs:element name="bidId" type="xs:string" minOccurs="0"/>
    </xs:sequence>
  </xs:complexType>
  <xs:complexType name="removeBidResponse">
    <xs:sequence>
      <xs:element ref="ns1:removeBidResponse" minOccurs="0"/>
    </xs:sequence>
  </xs:complexType>
  <xs:complexType name="getAllBids">
    <xs:sequence/>
  </xs:complexType>
  <xs:complexType name="getAllBidsResponse">
    <xs:sequence>
      <xs:element ref="ns1:getAllBidsResponse" minOccurs="0" maxOccurs="unbounded"/>
    </xs:sequence>
  </xs:complexType>
  <xs:complexType name="changeBidAmount">
    <xs:sequence>
      <xs:element name="bidId" type="xs:string" minOccurs="0"/>
      <xs:element name="newAmount" type="xs:double"/>
    </xs:sequence>
  </xs:complexType>
  <xs:complexType name="changeBidAmountResponse">
    <xs:sequence>
      <xs:element ref="ns1:changeBidAmountResponse" minOccurs="0"/>
    </xs:sequence>
  </xs:complexType>
</xs:schema>]]></con:content><con:type>http://www.w3.org/2001/XMLSchema</con:type></con:part><con:part><con:url>http://10.207.67.239:7011/BidService/ApiBidService?xsd=4</con:url><con:content><![CDATA[<!--Published by JAX-WS RI at http://jax-ws.dev.java.net. RI's version is Oracle JAX-WS 2.1.5.-->
<xs:schema version="1.0" targetNamespace="http://www.auction.com/api/adf/bidservice/ebm" xmlns:tns="http://www.auction.com/api/adf/bidservice/ebm" xmlns:ns1="http://www.auction.com/api/adf/bidservice/ebo" xmlns:xs="http://www.w3.org/2001/XMLSchema">
  <xs:import namespace="http://www.auction.com/api/adf/bidservice/ebo" schemaLocation="http://10.207.67.239:7011/BidService/ApiBidService?xsd=3"/>
  <xs:element name="addNewBid" type="tns:addNewBid"/>
  <xs:element name="addNewBidResponse" type="tns:addNewBidResponse"/>
  <xs:element name="changeBidAmountResponse" type="xs:string"/>
  <xs:element name="getAllBidsResponse" type="xs:string"/>
  <xs:element name="getHighBidsResponse" type="xs:string"/>
  <xs:element name="removeBidResponse" type="xs:string"/>
  <xs:complexType name="addNewBid">
    <xs:sequence>
      <xs:element ref="ns1:bid" minOccurs="0"/>
    </xs:sequence>
  </xs:complexType>
  <xs:complexType name="addNewBidResponse">
    <xs:sequence>
      <xs:element ref="ns1:bidResponse" minOccurs="0"/>
    </xs:sequence>
  </xs:complexType>
</xs:schema>]]></con:content><con:type>http://www.w3.org/2001/XMLSchema</con:type></con:part><con:part><con:url>http://10.207.67.239:7011/BidService/ApiBidService?xsd=3</con:url><con:content><![CDATA[<!--Published by JAX-WS RI at http://jax-ws.dev.java.net. RI's version is Oracle JAX-WS 2.1.5.-->
<xs:schema version="1.0" targetNamespace="http://www.auction.com/api/adf/bidservice/ebo" xmlns:xs="http://www.w3.org/2001/XMLSchema">
  <xs:element name="bid">
    <xs:complexType>
      <xs:sequence>
        <xs:element name="bidderId" type="xs:long" form="qualified" nillable="true"/>
        <xs:element name="itemId" type="xs:string" form="qualified" nillable="true"/>
        <xs:element name="amount" type="xs:double" form="qualified" nillable="true"/>
      </xs:sequence>
    </xs:complexType>
  </xs:element>
  <xs:element name="bidResponse">
    <xs:complexType>
      <xs:sequence>
        <xs:element name="response" type="xs:string" form="qualified"/>
      </xs:sequence>
    </xs:complexType>
  </xs:element>
</xs:schema>]]></con:content><con:type>http://www.w3.org/2001/XMLSchema</con:type></con:part></con:definitionCache><con:endpoints><con:endpoint>http://10.207.67.239:7011/BidService/ApiBidService</con:endpoint></con:endpoints><con:operation isOneWay="false" auction="http://localhost.localdomain:7011/BidService/ApiBidService/addNewBid" name="addNewBid" bindingOperationName="addNewBid" type="Request-Response" inputName="" receivesAttachments="false" sendsAttachments="false" anonymous="optional"><con:settings/><con:call name="Request 1"><con:settings><con:setting id="com.eviware.soapui.impl.wsdl.WsdlRequest@request-headers">&lt;xml-fragment/></con:setting></con:settings><con:encoding>UTF-8</con:encoding><con:endpoint>http://10.207.67.239:7011/BidService/ApiBidService</con:endpoint><con:request><![CDATA[<soapenv:Envelope xmlns:soapenv="http://schemas.xmlsoap.org/soap/envelope/" xmlns:ebm="http://www.auction.com/api/adf/bidservice/ebm" xmlns:ebo="http://www.auction.com/api/adf/bidservice/ebo">
   <soapenv:Header/>
   <soapenv:Body>
      <ebm:addNewBid>
         <!--Optional:-->
         <ebo:bid>
            <ebo:bidderId>1</ebo:bidderId>
            <ebo:itemId>5</ebo:itemId>
            <ebo:amount>4.0</ebo:amount>
         </ebo:bid>
      </ebm:addNewBid>
   </soapenv:Body>
</soapenv:Envelope>]]></con:request><con:jmsConfig JMSDeliveryMode="PERSISTENT"/><con:jmsPropertyConfig/><con:wsaConfig mustUnderstand="NONE" version="200508" auction="http://localhost.localdomain:7011/BidService/ApiBidService/addNewBid"/><con:wsrmConfig version="1.2"/></con:call></con:operation><con:operation isOneWay="false" auction="http://localhost.localdomain:7011/BidService/ApiBidService/changeBid" name="changeBidAmount" bindingOperationName="changeBidAmount" type="Request-Response" inputName="" receivesAttachments="false" sendsAttachments="false" anonymous="optional"><con:settings/><con:call name="Request 1"><con:settings/><con:encoding>UTF-8</con:encoding><con:endpoint>http://10.207.67.239:7011/BidService/ApiBidService</con:endpoint><con:request><![CDATA[<soapenv:Envelope xmlns:soapenv="http://schemas.xmlsoap.org/soap/envelope/" xmlns:ser="http://www.auction.com/api/adf/bidservice/service">
   <soapenv:Header/>
   <soapenv:Body>
      <ser:changeBidAmount>
         <!--Optional:-->
         <bidId>?</bidId>
         <newAmount>?</newAmount>
      </ser:changeBidAmount>
   </soapenv:Body>
</soapenv:Envelope>]]></con:request><con:wsaConfig mustUnderstand="NONE" version="200508" auction="http://localhost.localdomain:7011/BidService/ApiBidService/changeBid"/></con:call></con:operation><con:operation isOneWay="false" auction="http://localhost.localdomain:7011/BidService/ApiBidService/allBids" name="getAllBids" bindingOperationName="getAllBids" type="Request-Response" inputName="" receivesAttachments="false" sendsAttachments="false" anonymous="optional"><con:settings/><con:call name="Request 1"><con:settings/><con:encoding>UTF-8</con:encoding><con:endpoint>http://10.207.67.239:7011/BidService/ApiBidService</con:endpoint><con:request><![CDATA[<soapenv:Envelope xmlns:soapenv="http://schemas.xmlsoap.org/soap/envelope/" xmlns:ser="http://www.auction.com/api/adf/bidservice/service">
   <soapenv:Header/>
   <soapenv:Body>
      <ser:getAllBids/>
   </soapenv:Body>
</soapenv:Envelope>]]></con:request><con:wsaConfig mustUnderstand="NONE" version="200508" auction="http://localhost.localdomain:7011/BidService/ApiBidService/allBids"/></con:call></con:operation><con:operation isOneWay="false" auction="http://localhost.localdomain:7011/BidService/ApiBidService/higherBids" name="getHigherBids" bindingOperationName="getHigherBids" type="Request-Response" inputName="" receivesAttachments="false" sendsAttachments="false" anonymous="optional"><con:settings/><con:call name="Request 1"><con:settings/><con:encoding>UTF-8</con:encoding><con:endpoint>http://10.207.67.239:7011/BidService/ApiBidService</con:endpoint><con:request><![CDATA[<soapenv:Envelope xmlns:soapenv="http://schemas.xmlsoap.org/soap/envelope/" xmlns:ser="http://www.auction.com/api/adf/bidservice/service">
   <soapenv:Header/>
   <soapenv:Body>
      <ser:getHigherBids>
         <amountHigherThan>?</amountHigherThan>
      </ser:getHigherBids>
   </soapenv:Body>
</soapenv:Envelope>]]></con:request><con:wsaConfig mustUnderstand="NONE" version="200508" auction="http://localhost.localdomain:7011/BidService/ApiBidService/higherBids"/></con:call></con:operation><con:operation isOneWay="false" auction="http://localhost.localdomain:7011/BidService/ApiBidService/removeBid" name="removeBid" bindingOperationName="removeBid" type="Request-Response" inputName="" receivesAttachments="false" sendsAttachments="false" anonymous="optional"><con:settings/><con:call name="Request 1"><con:settings/><con:encoding>UTF-8</con:encoding><con:endpoint>http://10.207.67.239:7011/BidService/ApiBidService</con:endpoint><con:request><![CDATA[<soapenv:Envelope xmlns:soapenv="http://schemas.xmlsoap.org/soap/envelope/" xmlns:ser="http://www.auction.com/api/adf/bidservice/service">
   <soapenv:Header/>
   <soapenv:Body>
      <ser:removeBid>
         <!--Optional:-->
         <bidId>?</bidId>
      </ser:removeBid>
   </soapenv:Body>
</soapenv:Envelope>]]></con:request><con:wsaConfig mustUnderstand="NONE" version="200508" auction="http://localhost.localdomain:7011/BidService/ApiBidService/removeBid"/></con:call></con:operation></con:interface><con:properties/><con:wssContainer/></con:soapui-project>